qgis_plugins/__init__.py
qgis_plugins/generate.py
QGIS_plugins.xml-1.0.0.dist-info/LICENSE.txt
QGIS_plugins.xml-1.0.0.dist-info/METADATA
QGIS_plugins.xml-1.0.0.dist-info/WHEEL
QGIS_plugins.xml-1.0.0.dist-info/entry_points.txt
QGIS_plugins.xml-1.0.0.dist-info/top_level.txt
QGIS_plugins.xml-1.0.0.dist-info/RECORD
